better_dash_callback/__init__.py
better_dash_callback/src.py
better_dash_callback-0.1.5.dist-info/LICENSE
better_dash_callback-0.1.5.dist-info/METADATA
better_dash_callback-0.1.5.dist-info/WHEEL
better_dash_callback-0.1.5.dist-info/top_level.txt
better_dash_callback-0.1.5.dist-info/RECORD
